droppy/__init__.py
droppy/Form/_HLCL.py
droppy/Form/_MHLGA.py
droppy/Form/__init__.py
droppy/Reader/__init__.py
droppy/Reader/arianeReader.py
droppy/Reader/bvFormat.py
droppy/Reader/bvHdf5.py
droppy/Reader/donFormat.py
droppy/Reader/dynProbeReader.py
droppy/Reader/json_tools.py
droppy/Reader/openFoam.py
droppy/Reader/readInput.py
droppy/Reader/read_csv_block.py
droppy/Reader/simpleReader.py
droppy/Reader/tecplot.py
droppy/TimeDomain/TimeSignals.py
droppy/TimeDomain/__init__.py
droppy/TimeDomain/concat_time_series.py
droppy/TimeDomain/decayTest.py
droppy/TimeDomain/decluster.py
droppy/TimeDomain/forcedOscillation.py
droppy/TimeDomain/oneDof.py
droppy/TimeDomain/slamImpact.py
droppy/TimeDomain/srs.py
droppy/TimeDomain/upCross.py
droppy/interpolate/__init__.py
droppy/interpolate/cmplxInterp.py
droppy/interpolate/dfInterpolate.py
droppy/interpolate/linInterp.py
droppy/numerics/__init__.py
droppy/numerics/iso_contour.py
droppy/numerics/numerical_jacobian.py
droppy/pyplotTools/__init__.py
droppy/pyplotTools/_scatterPlot.py
droppy/pyplotTools/addcopyfighandler.py
droppy/pyplotTools/concatPlot.py
droppy/pyplotTools/customScale.py
droppy/pyplotTools/dfPlot.py
droppy/pyplotTools/geoMap.py
droppy/pyplotTools/gnuplot_compat.py
droppy/pyplotTools/meshPlot.py
droppy/pyplotTools/misc.py
droppy/pyplotTools/mplZoom.py
droppy/pyplotTools/statPlots.py
droppy/pyplotTools/surfacePlot.py
droppy/pyplotTools/video_overlay.py
droppy/pyplotTools/vtkLUT.py
droppy/tools/__init__.py
droppy/tools/deprecated.py
droppy_bv-1.0.14.dist-info/LICENSE
droppy_bv-1.0.14.dist-info/METADATA
droppy_bv-1.0.14.dist-info/WHEEL
droppy_bv-1.0.14.dist-info/top_level.txt
droppy_bv-1.0.14.dist-info/RECORD
