Metadata-Version: 2.1
Name: droppy-bv
Version: 1.0.14
Summary: Research Department BV M&O open library, related to waves and sea-keeping
Home-page: https://github.com/BV-DR/droppy
Author: Research Department BV M&O
Author-email: UNKNOWN
License: UNKNOWN
Platform: UNKNOWN
Classifier: Intended Audience :: Science/Research
Classifier: Topic :: Scientific/Engineering
Classifier: License :: OSI Approved :: GNU General Public License v3 or later (GPLv3+)
Classifier: Programming Language :: Python :: 3.7
Classifier: Programming Language :: Python :: 3.8
Classifier: Programming Language :: Python :: 3.9
Classifier: Operating System :: OS Independent
Requires-Dist: Deprecated
Requires-Dist: contourpy
Requires-Dist: h5py
Requires-Dist: ipython
Requires-Dist: matplotlib
Requires-Dist: numpy (>=1.18)
Requires-Dist: pandas (>=1.0)
Requires-Dist: scipy (>=1.5)
Requires-Dist: tqdm
Requires-Dist: xarray
